ezusergen/__init__.py
ezusergen/ezusergen.py
ezusergen-0.1.3.dist-info/LICENSE
ezusergen-0.1.3.dist-info/METADATA
ezusergen-0.1.3.dist-info/WHEEL
ezusergen-0.1.3.dist-info/top_level.txt
ezusergen-0.1.3.dist-info/RECORD
