Metadata-Version: 2.1
Name: ezusergen
Version: 0.1.3
Summary: A simple username generator that combines random words with numbers
Home-page: https://github.com/Ondry4K/ezusergen
Author: Ondry
Author-email: ondrygfx@gmail.com
Classifier: Programming Language :: Python :: 3
Classifier: License :: OSI Approved :: MIT License
Classifier: Operating System :: OS Independent
Requires-Python: >=3.6
License-File: LICENSE
Requires-Dist: requests
